LICENSE
MANIFEST.in
README.md
setup.py
evnn_pytorch.egg-info/PKG-INFO
evnn_pytorch.egg-info/SOURCES.txt
evnn_pytorch.egg-info/dependency_links.txt
evnn_pytorch.egg-info/requires.txt
evnn_pytorch.egg-info/top_level.txt
frameworks/pytorch/__init__.py
frameworks/pytorch/_version.py
frameworks/pytorch/base_rnn.py
frameworks/pytorch/egru.cc
frameworks/pytorch/egru.py
frameworks/pytorch/support.cc
frameworks/pytorch/support.h
lib/blas.h
lib/device_assert.h
lib/egru_backward_cpu.cc
lib/egru_backward_gpu.cu
lib/egru_forward_cpu.cc
lib/egru_forward_gpu.cu
lib/evnn.h
lib/inline_ops.h
lib/evnn/egru.h
lib/evnn/egru_cpu.h