Metadata-Version: 2.1
Name: evnn_pytorch
Version: 0.2.0
Summary: EVNN: a torch extension for custom event based RNN models.
Home-page: https://tu-dresden.de/ing/elektrotechnik/iee/hpsn
Author: TUD and RUB
Author-email: khaleelulla.khan_nazeer@tu-dresden.de
License: Apache 2.0
Keywords: pytorch machine learning rnn lstm gru custom op
Classifier: Development Status :: 4 - Beta
Classifier: Intended Audience :: Developers
Classifier: Intended Audience :: Education
Classifier: Intended Audience :: Science/Research
Classifier: License :: OSI Approved :: Apache Software License
Classifier: Programming Language :: Python :: 3.10
Classifier: Programming Language :: Python :: 3.11
Classifier: Topic :: Scientific/Engineering :: Mathematics
Classifier: Topic :: Software Development :: Libraries :: Python Modules
Classifier: Topic :: Software Development :: Libraries
License-File: LICENSE
Requires-Dist: torch
